collect_homework/cli.py
collect_homework/parallel_shells.py
collect_homework-0.4.1.dist-info/METADATA
collect_homework-0.4.1.dist-info/WHEEL
collect_homework-0.4.1.dist-info/entry_points.txt
collect_homework-0.4.1.dist-info/RECORD
