Metadata-Version: 2.4
Name: collect-homework
Version: 0.4.1
Summary: Easily manage homework submissions
Project-URL: Repository, https://github.com/flotpython/collect-homework
Project-URL: Bug Tracker, https://github.com/flotpython/collect-homework/issues
Author-email: Thierry Parmentelat <thierry.parmentelat@minesparis.psl.eu>
License: MIT License
Keywords: github,homework,submissions
Requires-Python: >=3.8
Requires-Dist: click
